dsc/array_mul/2_input/4b/array_mul.v
`timescale 1 ns / 100 ps

`define BITS 4
`define NUM_INPUTS 2

module FA (
  a,
  b,
  cin,
  s,
  cout
);
   input a,b,cin;
   output s,cout;

   wire   xor_int, and0_int, and1_int;

   assign xor_int = a ^ b;
   assign and0_int = xor_int & cin;
   assign and1_int = a & b;
   
   

   assign s = xor_int^cin;
   assign cout = and0_int | and1_int;
   

endmodule // FA

module HA (
  a,
  b,
  s,
  cout
);

   input a,b;
   output s,cout;

   assign s = a ^ b;
   assign cout = a & b;
   

endmodule // HA


module array_mul (
    a,
    b,
    z);

   input  [`BITS-1:0] a,b;
   output [(`NUM_INPUTS*`BITS)-1:0] z;

   wire [`BITS*(`BITS-1)-1:0]       c;
   wire [`BITS*(`BITS-1)-1:0]       s;
   wire                             pp00;
   wire                             pp01;
   wire                             pp02;
   wire                             pp03;
   wire                             pp10;
   wire                             pp11;
   wire                             pp12;
   wire                             pp13;
   wire                             pp20;
   wire                             pp21;
   wire                             pp22;
   wire                             pp23;
   wire                             pp30;
   wire                             pp31;
   wire                             pp32;
   wire                             pp33;

   assign pp00 = a[0] & b[0];
   assign pp01 = a[0] & b[1];
   assign pp02 = a[0] & b[2];
   assign pp03 = a[0] & b[3];
   assign pp10 = a[1] & b[0];
   assign pp11 = a[1] & b[1];
   assign pp12 = a[1] & b[2];
   assign pp13 = a[1] & b[3];
   assign pp20 = a[2] & b[0];
   assign pp21 = a[2] & b[1];
   assign pp22 = a[2] & b[2];
   assign pp23 = a[2] & b[3];
   assign pp30 = a[3] & b[0];
   assign pp31 = a[3] & b[1];
   assign pp32 = a[3] & b[2];
   assign pp33 = a[3] & b[3];
   
   

   assign z[0] = pp00;
   //level0   
   HA ha0 (.a(pp10),.b(pp01),.s(s[0]),.cout(c[0]));
   HA ha1 (.a(pp20),.b(pp11),.s(s[1]),.cout(c[1]));
   HA ha2 (.a(pp30),.b(pp31),.s(s[2]),.cout(c[2]));

   assign z[1] = s[0];
   
   //level1   
   FA fa3 (.a(s[1]),.b(c[0]),.cin(pp02),.s(s[3]),.cout(c[3]));
   FA fa4 (.a(s[2]),.b(c[1]),.cin(pp12),.s(s[4]),.cout(c[4]));
   FA fa5 (.a(pp31),.b(c[2]),.cin(pp22),.s(s[5]),.cout(c[5]));

   assign z[2] = s[3];

   //level2
   FA fa6 (.a(s[4]),.b(c[3]),.cin(pp03),.s(s[6]),.cout(c[6]));
   FA fa7 (.a(s[5]),.b(c[4]),.cin(pp13),.s(s[7]),.cout(c[7]));
   FA fa8 (.a(pp32),.b(c[5]),.cin(pp23),.s(s[8]),.cout(c[8]));

   assign z[3] = s[6];

   //level3 - RCA
   HA ha9 (.a(s[7]),.b(c[6]),            .s(s[9]) ,.cout(c[9]));
   FA fa10(.a(s[8]),.b(c[7]),.cin(c[9]) ,.s(s[10]),.cout(c[10]));
   FA fa11(.a(pp33),.b(c[8]),.cin(c[10]),.s(s[11]),.cout(c[11]));

   assign z[4] = s[9];
   assign z[5] = s[10];
   assign z[6] = s[11];
   assign z[7] = c[11];
   
   
   
   

   



endmodule // dsc_mul

dsc/array_mul/2_input/4b/array_mul_tb.v
`timescale 1 ns / 100 ps

`define NUM_TESTS 1000
`define NUM_INPUTS 2
`define NUM_BITS 4



module dsc_mul_tb ();
//--------------------------------------------------------- // inputs to the DUT are reg type
   reg clk_50;
   reg en;
   reg rst;

   reg [`NUM_BITS-1:0] input_bin_a, input_bin_b;
   
   
   
//-------------------------------------------------------- // outputs from the DUT are wire type
   //wire [3-1  :0] ctr3_out;
   //wire           ctr3_overflow;
   //
   //wire [2-1  :0] ctr2_out;
   //wire           ctr2_overflow;
   //wire [3:0] ctr4_out_a,ctr4_out_b;
   //wire       ctr4_overflow_a,ctr4b_overflow_b;
   
   //wire           sn_out_a,sn_out_b,sn_mul_out;

   wire [`NUM_INPUTS*`NUM_BITS-1:0]     bin_out;
   //wire           bin_out_overflow;
   wire           op_finished;

   //wire [7:0]     expected;
   longint       expected_result;
   //int            cycle_count;
   //int            time_start,time_end;

   wire [100:0]    cycle_count;
   wire           cycle_count_overflow;
   
   
            
   
      
   

   integer        i;
   real            cycle_count_acc;
            
   
           
   
   
   
   

   
//--------------------------------------------------------- // instantiate the Device Under Test (DUT)
// using named instantiation



//counter #(
//   .WIDTH (4)
//) dut_ctr4 (
//  .clk(clk_50),
//  .rst(rst),
//  .en(en),
//  .out(ctr4_out),
//  .overflow(ctr4_overflow)
//);
//
//
//   //comparator2 dut_comp2 ( .a(input_bin), .b(ctr2_out), .y(sn_out));
//
//   comp_4b     dut_comp4 (.a(input_bin), .b(ctr4_out), .a_gt_b(sn_out));

//bin2stoch a   
/////prg_4b dut_prg4b_a (
/////  .clk(clk_50),
/////  .rst(rst),
/////  .en(en),
/////  .bin_in(input_bin_a),
/////  .sn_out(sn_out_a),
/////  .ctr_overflow(ctr4_overflow_a)         
/////);
/////
///////bin2stoch b
/////prg_4b dut_prg4b_b (
/////  .clk(ctr4_overflow_a),
/////  .rst(rst),
/////  .en(en),
/////  .bin_in(input_bin_b),
/////  .sn_out(sn_out_b),
/////  .ctr_overflow(ctr4_overflow_b)         
/////);
/////
///////multiplier circuit
/////det_stoch_mul dut_mul (
/////  .a(sn_out_a),
/////  .b(sn_out_b),
/////  .y(sn_mul_out)
/////);
/////                       
///////stoch2bin out
/////counter #(
/////  .WIDTH (8)
/////) stoch2bin_out (
/////  .clk(clk_50),
/////  .rst(rst),
/////  .en(sn_mul_out),
/////  .out(bin_out),
/////  .overflow(bin_out_overflow)
/////);

array_mul dut (
  .a(input_bin_a),
  .b(input_bin_b),
  .z(bin_out)
);
   
//count number of clock cycles here
//TODO//                   

///counter #(.WIDTH(100)) cycle_counter (
///  .clk(clk_50),
///  .rst(rst),
///  .en(en),
///  .out(cycle_count),
///  .overflow(cycle_count_overflow)
///);
   


   

   
//---------------------------------------------------------- // create a 50Mhz clock
always
    #10 clk_50 = ~clk_50;   // every ten nanoseconds invert
//----------------------------------------------------------- // initial blocks are sequential and start at time 0
  initial
    begin

       $dumpfile ("dsc_mul_tb.vcd");
       $dumpvars(0,dsc_mul_tb);
       $vcdplusfile("dsc_mul_tb.vpd");
       $vcdpluson(0,dsc_mul_tb);
       
       
    $display($time, " << Starting the Simulation >>");
       clk_50 = 0;
       en = 0;
       rst = 1;
       input_bin_a = 0;
       input_bin_b = 0;
       
       
       #10
       rst = 0;
       
       #10
       en  = 1;
       input_bin_a = 15;
       input_bin_b = 15;

       for(i=0;i<`NUM_TESTS;i=i+1)
         begin
            //$display("iteration %d",i);
            input_bin_a = $random();
            input_bin_b = $random();
            
            #10 rst = 0;
            #10 en = 1;

           //@(posedge clk_50)
           //  begin
           //     $display("alex");
           //     cycle_count = cycle_count + 1;
           //  end

            //time_start = $time;
            expected_result = input_bin_a * input_bin_b;
            
            
            
            
            //wait(op_finished);
            //time_end = $time;
            #20
            
            //expected_result = input_bin_a * input_bin_b;
            //cycle_count = time_end - time_start;
            cycle_count_acc += cycle_count;
            
            
            $display("Test %d : a=%d, b=%d, z=%d",i,input_bin_a,input_bin_b,bin_out);
            

            if(expected_result != bin_out) begin
               $display("ERROR : a=%d, b=%d, z=%d, expected=%d",input_bin_a,input_bin_b,bin_out,expected_result);
            end
            
            
            //$display("alex : expected : %d * %d = %d", input_bin_a, input_bin_b, expected_result);
            //$display("alex : obtained : %d",bin_out);
            rst = 1;
            en  = 0;
            //cycle_count = 0;
            
            
              
         end
       
       
       

       

         

       //wait(op_finished == 1);
       
       //#10

       

       
       
       
       
       
       
       
       
       
                                  
    //wait ((ctr3_out == 8'hff))
    
    //wait ({a,b,par,c} == 10'b1111111111)
    //#1000
       
    $display("Average cycle time : %f",cycle_count_acc/`NUM_TESTS);
    $display(" << Simulation Complete >> ");
       
    //$stop; // stop the simulation
    $finish; //stop similation and give control back to OS
  end // initial begin


//-------------------------------------------------------------- // This initial block runs concurrently with the other
// blocks in the design and starts at time 0
   //integer i;
   //reg    parity_check;
   //reg    c_one_hot;
   //reg    input_good;
   
   
   
   
 initial begin
    //$monitor($time, " rst=%b, en=%b, bin_a=%h, bin_b=%h, ctr_a=%h, ctr_b=%h, ov_a=%b, ov_b=%b, sn_a=%b, sn_b=%b,mul_out=%b,bin_out=%h",
    //         rst, 
    //         en, 
    //         input_bin_a, 
    //         input_bin_b, 
    //         dsc_mul_es_imp_tb.dut.prg_a.ctr4_out, 
    //         dsc_mul_es_imp_tb.dut.prg_b.ctr4_out, 
    //         dsc_mul_es_imp_tb.dut.ctr_ov_a, 
    //         dsc_mul_es_imp_tb.dut.ctr_ov_b, 
    //         dsc_mul_es_imp_tb.dut.sn_out_a,
    //         dsc_mul_es_imp_tb.dut.sn_out_b,
    //         dsc_mul_es_imp_tb.dut.sn_out_mul,
    //         bin_out);
    
    
 
   
    
    
    
// always @ (posedge clk_50)
    //   a = a+1;
    // end
     
  end
//-------------------------------------------------------------- // The load_count task loads the counter with the value passed
//  task load_count;
//     input [3:0] load_value;
//     begin
//@(negedge clk_50);
//$display($time, " << Loading the counter with %h >>", load_value); load_l = 1’b0;
//count_in = load_value;
//@(negedge clk_50);
//load_l = 1’b1;
//     end
//  endtask //of load_count
endmodule //of cnt16_tb

dsc/array_mul/2_input/4b/dsc_mul_tb.vcd
$date
	Wed Mar 27 01:44:58 2019
$end

$version
	Synopsys VCS version K-2015.09-SP1_Full64
$end

$timescale
	100ps
$end

$comment Csum: 1 ee0f70cd7b1c1c75 $end


$scope module dsc_mul_tb $end
$var reg 1 ! clk_50 $end
$var reg 1 " en $end
$var reg 1 # rst $end
$var reg 4 $ input_bin_a [3:0] $end
$var reg 4 % input_bin_b [3:0] $end
$var wire 8 & bin_out [7:0] $end
$var wire 1 ' op_finished $end
$var reg 64 ( expected_result [63:0] $end
$var wire 101 ) cycle_count [100:0] $end
$var wire 1 * cycle_count_overflow $end
$var integer 32 + i $end
$var real 64 , cycle_count_acc $end

$scope module dut $end
$var wire 4 $ a [3:0] $end
$var wire 4 % b [3:0] $end
$var wire 8 & z [7:0] $end
$var wire 12 - c [11:0] $end
$var wire 12 . s [11:0] $end
$var wire 1 / pp00 $end
$var wire 1 0 pp01 $end
$var wire 1 1 pp02 $end
$var wire 1 2 pp03 $end
$var wire 1 3 pp10 $end
$var wire 1 4 pp11 $end
$var wire 1 5 pp12 $end
$var wire 1 6 pp13 $end
$var wire 1 7 pp20 $end
$var wire 1 8 pp21 $end
$var wire 1 9 pp22 $end
$var wire 1 : pp23 $end
$var wire 1 ; pp30 $end
$var wire 1 < pp31 $end
$var wire 1 = pp32 $end
$var wire 1 > pp33 $end

$scope module ha0 $end
$var wire 1 3 a $end
$var wire 1 0 b $end
$var wire 1 ? s $end
$var wire 1 @ cout $end
$upscope $end


$scope module ha1 $end
$var wire 1 7 a $end
$var wire 1 4 b $end
$var wire 1 A s $end
$var wire 1 B cout $end
$upscope $end


$scope module ha2 $end
$var wire 1 ; a $end
$var wire 1 < b $end
$var wire 1 C s $end
$var wire 1 D cout $end
$upscope $end


$scope module fa3 $end
$var wire 1 A a $end
$var wire 1 @ b $end
$var wire 1 1 cin $end
$var wire 1 E s $end
$var wire 1 F cout $end
$var wire 1 G xor_int $end
$var wire 1 H and0_int $end
$var wire 1 I and1_int $end
$upscope $end


$scope module fa4 $end
$var wire 1 C a $end
$var wire 1 B b $end
$var wire 1 5 cin $end
$var wire 1 J s $end
$var wire 1 K cout $end
$var wire 1 L xor_int $end
$var wire 1 M and0_int $end
$var wire 1 N and1_int $end
$upscope $end


$scope module fa5 $end
$var wire 1 < a $end
$var wire 1 D b $end
$var wire 1 9 cin $end
$var wire 1 O s $end
$var wire 1 P cout $end
$var wire 1 Q xor_int $end
$var wire 1 R and0_int $end
$var wire 1 S and1_int $end
$upscope $end


$scope module fa6 $end
$var wire 1 J a $end
$var wire 1 F b $end
$var wire 1 2 cin $end
$var wire 1 T s $end
$var wire 1 U cout $end
$var wire 1 V xor_int $end
$var wire 1 W and0_int $end
$var wire 1 X and1_int $end
$upscope $end


$scope module fa7 $end
$var wire 1 O a $end
$var wire 1 K b $end
$var wire 1 6 cin $end
$var wire 1 Y s $end
$var wire 1 Z cout $end
$var wire 1 [ xor_int $end
$var wire 1 \ and0_int $end
$var wire 1 ] and1_int $end
$upscope $end


$scope module fa8 $end
$var wire 1 = a $end
$var wire 1 P b $end
$var wire 1 : cin $end
$var wire 1 ^ s $end
$var wire 1 _ cout $end
$var wire 1 ` xor_int $end
$var wire 1 a and0_int $end
$var wire 1 b and1_int $end
$upscope $end


$scope module ha9 $end
$var wire 1 Y a $end
$var wire 1 U b $end
$var wire 1 c s $end
$var wire 1 d cout $end
$upscope $end


$scope module fa10 $end
$var wire 1 ^ a $end
$var wire 1 Z b $end
$var wire 1 d cin $end
$var wire 1 e s $end
$var wire 1 f cout $end
$var wire 1 g xor_int $end
$var wire 1 h and0_int $end
$var wire 1 i and1_int $end
$upscope $end


$scope module fa11 $end
$var wire 1 > a $end
$var wire 1 _ b $end
$var wire 1 f cin $end
$var wire 1 j s $end
$var wire 1 k cout $end
$var wire 1 l xor_int $end
$var wire 1 m and0_int $end
$var wire 1 n and1_int $end
$upscope $end

$upscope $end

$upscope $end

$enddefinitions $end

#0
$dumpvars
0!
z*
0"
z'
00
04
1#
x3
x7
x;
x8
x/
b00000000 &
bzzzzzzzzzzzzzzzzzzzzzzzzzzzzzzzzzzzzzzzzzzzzzzzzzzzzzzzzzzzzzzzzzzzzzzzzzzzzzzzzzzzzzzzzzzzzzzzzzzzzz )
bxxxxxxxxxxxxxxxxxxxxxxxxxxxxxxxx +
b0000 $
b0000 %
b0000000000000000000000000000000000000000000000000000000000000000 (
r0.000000000000000  ,
0H
0I
0G
0M
0N
0L
0R
0S
0Q
0W
0X
0V
0\
0]
0[
0a
0b
0`
0h
0i
0g
0m
0n
0l
b000000000000 -
b000000000000 .
0<
0@
0B
0D
0d
0?
0A
0C
0c
01
05
09
0=
02
06
0:
0>
0E
0F
0J
0K
0O
0P
0T
0U
0Y
0Z
0^
0_
0e
0f
0j
0k
$end
08
0/
03
07
0;
#100
1!
0#
#200
0!
1"
b1111 $
18
b1111 %
1/
13
17
1;
11
15
19
1=
1`
12
16
1:
1>
1l
1<
1Q
14
10
b00000000000000000000000000000000 +
b0100 $
00
04
0<
0Q
02
06
0>
0l
01
05
0=
0`
0/
03
0;
b0001 %
08
09
0:
1A
1G
1E
0R
0a
b00000100 &
b000000001010 .
#300
1!
#400
0!
b0000000000000000000000000000000000000000000000000000000000000100 (
#500
1!
#600
1#
0"
b00000000000000000000000000000001 +
b1001 $
1/
07
1;
b0011 %
1<
1Q
10
0!
0A
0G
1D
1S
0Q
0E
1P
1`
1^
1g
1e
b00100000 &
1?
b010100000001 .
b000000100100 -
b00100011 &
#700
0#
1!
#800
1"
b0000000000000000000000000000000000000000000000000000000000011011 (
0!
#900
1!
#1000
1#
0"
b00000000000000000000000000000010 +
b1101 $
18
17
b1101 %
08
11
19
1=
1b
0`
12
1:
1>
1l
0<
0S
1Q
00
0!
1A
1G
0D
0Q
1C
1L
1H
1O
1[
0R
1J
1V
1F
1X
0V
1T
0P
0b
1`
0W
0^
0g
1Y
1c
1U
1d
0c
1a
1_
1n
0l
1k
b10101011 &
0?
b010011110110 .
b101101001000 -
b10101001 &
#1100
0#
1!
#1200
1"
b0000000000000000000000000000000000000000000000000000000010101001 (
0!
#1300
1!
#1400
1#
0"
b00000000000000000000000000000011 +
b0101 $
0>
0n
1l
0=
0`
0;
b0010 %
18
0/
07
01
09
02
0:
10
0!
0C
0L
1E
0H
0O
0[
0J
0X
1V
0F
0V
0T
0a
0Y
0d
1c
0U
0c
0_
0l
0e
0k
b00000101 &
0A
0G
1?
b000000001001 .
b000000000000 -
0E
b00000010 &
b000000000001 .
#1500
0#
1!
#1600
1"
b0000000000000000000000000000000000000000000000000000000000001010 (
0!
#1700
1!
#1800
1#
0"
b00000000000000000000000000000100 +
b0001 $
08
b1101 %
1/
11
12
00
0!
1E
1T
b00001110 &
0?
b000001001000 .
b00001101 &
#1900
0#
1!
#2000
1"
b0000000000000000000000000000000000000000000000000000000000001101 (
0!
#2100
1!
#2200
1#
0"
b00000000000000000000000000000101 +
b0110 $
02
16
1:
01
15
19
0/
13
17
0!
0E
1J
1V
1O
1[
1^
1g
1\
1Z
1i
0g
1f
1j
b01001001 &
1?
1A
1G
b100101110011 .
b010010000000 -
1E
b01001110 &
b100101111011 .
#2300
0#
1!
#2400
1"
b0000000000000000000000000000000000000000000000000000000001001110 (
0!
#2500
1!
#2600
1#
0"
b00000000000000000000000000000110 +
b1101 $
12
06
1>
1l
11
05
1=
1`
1/
03
1;
b1100 %
0/
07
0;
0!
0E
1H
0J
0V
1F
1V
0T
1W
1Y
1c
0\
0^
0i
1g
1a
1U
1d
0c
0Z
0g
1_
1n
0l
1e
0h
0f
0j
0m
1k
b10100010 &
0?
0A
0G
b010010100000 .
b101101001000 -
1E
0H
0F
0V
1T
0W
0U
0d
1c
0e
b10011100 &
b001011101000 .
b100100000000 -
#2700
0#
1!
#2800
1"
b0000000000000000000000000000000000000000000000000000000010011100 (
0!
#2900
1!
#3000
1#
0"
b00000000000000000000000000000111 +
b1001 $
0:
09
b0110 %
02
0>
0n
1l
1<
1Q
10
0!
1C
1L
1J
1V
1^
1g
0a
0_
0l
1e
0k
b00111100 &
1?
b011111111101 .
b000000000000 -
b00111110 &
#3100
0#
1!
#3200
1"
b0000000000000000000000000000000000000000000000000000000000110110 (
0!
#3300
1!
#3400
1#
0"
b00000000000000000000000000001000 +
b0101 $
18
0<
0Q
19
0=
0`
b1010 %
01
09
12
1:
0!
0C
0L
0E
0O
0[
0J
0V
0W
0Y
0c
b00101010 &
b010101000001 .
#3500
0#
1!
#3600
1"
b0000000000000000000000000000000000000000000000000000000000110010 (
0!
#3700
1!
#3800
1#
0"
b00000000000000000000000000001001 +
b0111 %
1/
17
11
19
02
0:
0!
1A
1G
1H
1O
1[
1F
1V
0^
0g
1Y
1c
0e
b00011010 &
b001011100011 .
b000000001000 -
b00011011 &
#3900
0#
1!
#4000
1"
b0000000000000000000000000000000000000000000000000000000000100011 (
0!
#4100
1!
#4200
1#
0"
b00000000000000000000000000001010 +
b0010 $
08
00
14
01
15
09
0/
13
07
b1111 %
16
0!
1E
0H
1J
1X
0V
0O
0[
0F
0X
1V
0\
b00011111 &
b001011011011 .
b000000000000 -
b00011110 &
#4300
0#
1!
#4400
1"
b0000000000000000000000000000000000000000000000000000000000011110 (
0!
#4500
1!
#4600
1#
0"
b00000000000000000000000000001011 +
b1110 %
03
0!
0?
b001011011010 .
b00011100 &
#4700
0#
1!
#4800
1"
b0000000000000000000000000000000000000000000000000000000000011100 (
0!
#4900
1!
#5000
1#
0"
b00000000000000000000000000001100 +
b1000 $
04
1<
1Q
06
1>
1l
05
1=
1`
b0101 %
1;
0>
0l
0<
0Q
0!
0A
0G
1C
1L
0E
0Y
0c
1^
1g
1e
b00101000 &
b010101010100 .
#5100
0#
1!
#5200
1"
b0000000000000000000000000000000000000000000000000000000000101000 (
0!
#5300
1!
#5400
1#
0"
b00000000000000000000000000001101 +
b1100 $
19
17
b1101 %
1:
1>
1l
0!
1O
1[
0^
0g
1a
1Y
1c
1_
1n
0l
0e
1k
b10011000 &
1A
1G
b001011110110 .
b100100000000 -
1E
b10011100 &
b001011111110 .
#5500
0#
1!
#5600
1"
b0000000000000000000000000000000000000000000000000000000010011100 (
0!
#5700
1!
#5800
1#
0"
b00000000000000000000000000001110 +
b1101 $
12
11
1/
b0101 %
02
0:
0>
0n
1l
0!
0E
1H
1F
1X
0V
0T
0W
1^
1g
0a
1U
1d
0c
0_
0l
1h
1f
1j
0k
b01000000 &
b100110110110 .
b011001001000 -
b01000001 &
#5900
0#
1!
#6000
1"
b0000000000000000000000000000000000000000000000000000000001000001 (
0!
#6100
1!
#6200
1#
0"
b00000000000000000000000000001111 +
b0011 $
15
09
0=
0`
13
07
0;
b1010 %
0/
03
01
05
12
16
14
10
0!
0C
0L
1E
0H
0J
0X
1V
0M
0O
0[
0F
0V
1T
0W
0^
0g
0\
0U
0d
1c
0h
0f
0j
b00011101 &
1?
b001011001011 .
b000000000000 -
b00011111 &
b00011110 &
#6300
0#
1!
#6400
1"
b0000000000000000000000000000000000000000000000000000000000011110 (
0!
#6500
1!
#6600
1#
0"
b00000000000000000000000000010000 +
b0000 $
00
04
02
06
b0000 %
0!
0?
0A
0G
0E
0T
0Y
0c
b00000000 &
b000000000000 .
#6700
0#
1!
#6800
1"
b0000000000000000000000000000000000000000000000000000000000000000 (
0!
#6900
1!
#7000
1#
0"
b00000000000000000000000000010001 +
b1010 $
b1101 %
13
1;
15
1=
1`
16
1>
1l
0!
1?
1C
1L
1M
1K
1[
1^
1g
1\
1Z
1i
0g
1f
1m
1k
b10000010 &
b000100000101 .
b110010010000 -
#7100
0#
1!
#7200
1"
b0000000000000000000000000000000000000000000000000000000010000010 (
0!
#7300
1!
#7400
1#
0"
b00000000000000000000000000010010 +
b0110 $
1:
0>
0l
19
0=
0`
17
0;
b0011 %
18
05
09
06
0:
14
0!
0C
0L
0M
0K
0[
0^
0i
1g
0a
0\
0Z
0g
0f
0m
0k
b00000010 &
1B
1L
b000000000001 .
b000000000010 -
1J
1V
1T
b00001010 &
b000001010001 .
#7500
0#
1!
#7600
1"
b0000000000000000000000000000000000000000000000000000000000010010 (
0!
#7700
1!
#7800
1#
0"
b00000000000000000000000000010011 +
b1101 $
10
04
1<
1Q
1/
03
1;
0!
0B
0L
1A
1G
1D
1S
0Q
1E
0J
0V
1P
1`
0T
1^
1g
1e
b00100110 &
b000000100100 -
b010100001011 .
b00100111 &
#7900
0#
1!
#8000
1"
b0000000000000000000000000000000000000000000000000000000000100111 (
0!
#8100
1!
#8200
1#
0"
b00000000000000000000000000010100 +
b1011 $
08
14
13
07
b0101 %
11
15
1=
1b
0`
0<
0S
1Q
04
00
0!
0A
0G
0H
0D
0Q
1C
1L
1M
0P
0b
1`
1K
1[
1Y
1c
b00110111 &
b011110001101 .
b000000010000 -
#8300
0#
1!
#8400
1"
b0000000000000000000000000000000000000000000000000000000000110111 (
0!
#8500
1!
#8600
1#
0"
b00000000000000000000000000010101 +
b0010 $
01
0=
0`
0/
0;
b1110 %
03
16
14
0!
0E
0C
0L
1J
1V
0M
1T
0K
0[
0^
0g
0\
0e
b00011011 &
0?
1A
1G
b001011010010 .
b000000000000 -
1E
b00011100 &
b001011011010 .
#8700
0#
1!
#8800
1"
b0000000000000000000000000000000000000000000000000000000000011100 (
0!
#8900
1!
#9000
1#
0"
b00000000000000000000000000010110 +
b1101 $
18
10
04
1<
1Q
12
06
1:
1>
1l
11
05
19
1=
1`
b1111 %
1/
17
1;
0!
1?
0E
1H
1D
1S
0Q
1O
1[
0J
0V
0R
1F
1V
0T
1W
1P
1b
0`
1^
1g
0a
1U
1d
0c
1_
1n
0l
1h
1f
1j
1k
b11000010 &
b100110100011 .
b111101101100 -
b11000011 &
#9100
0#
1!
#9200
1"
b0000000000000000000000000000000000000000000000000000000011000011 (
0!
#9300
1!
#9400
1#
0"
b00000000000000000000000000010111 +
b0011 $
08
14
0<
0S
1Q
16
0:
0>
0n
1l
15
09
0=
0b
1`
13
07
0;
b1010 %
0/
03
01
05
0!
0D
0Q
1E
0H
0O
0[
0R
0F
0V
0P
0`
1T
0W
0\
0^
0g
0U
0d
1c
0_
0l
0h
0f
0j
0m
0k
b00011111 &
b000000000000 -
b001011001011 .
b00011110 &
#9500
0#
1!
#9600
1"
b0000000000000000000000000000000000000000000000000000000000011110 (
0!
#9700
1!
#9800
1#
0"
b00000000000000000000000000011000 +
b1010 $
00
1<
1Q
02
1>
1l
b1100 %
15
1=
1`
0<
0Q
04
0!
0?
1J
1V
1^
1g
1e
1j
b01111100 &
0A
0G
b111111011000 .
0E
b01111000 &
b111111010000 .
#9900
0#
1!
#10000
1"
b0000000000000000000000000000000000000000000000000000000001111000 (
0!
#10100
1!
#10200
1#
0"
b00000000000000000000000000011001 +
b0010 $
0>
0l
0=
0`
b1010 %
05
14
0!
0J
0V
0T
0^
0g
0e
0j
b00010000 &
1A
1G
b001010000010 .
1E
b00010100 &
b001010001010 .
#10300
0#
1!
#10400
1"
b0000000000000000000000000000000000000000000000000000000000010100 (
0!
#10500
1!
#10600
1#
0"
b00000000000000000000000000011010 +
b0001 $
10
04
12
06
b1000 %
00
0!
0A
0G
0E
1T
0Y
0c
b00001000 &
b000001000000 .
#10700
0#
1!
#10800
1"
b0000000000000000000000000000000000000000000000000000000000001000 (
0!
#10900
1!
#11000
1#
0"
b00000000000000000000000000011011 +
b1000 $
02
1>
1l
b1001 %
1;
0!
1C
1L
1J
1V
1j
b01001000 &
b100001010100 .
#11100
0#
1!
#11200
1"
b0000000000000000000000000000000000000000000000000000000001001000 (
0!
#11300
1!
#11400
1#
0"
b00000000000000000000000000011100 +
b1011 $
12
16
1/
13
b0110 %
0/
03
0;
11
15
1=
1`
02
06
0>
0l
1<
1Q
14
10
0!
1E
0J
0V
1M
1O
1[
0T
0W
1K
1]
0[
1^
1g
1Z
1i
0g
1f
b01000100 &
1?
1A
1G
b100100101111 .
b010010010000 -
0E
1H
1F
1V
1T
b01001010 &
b100101100111 .
b010010011000 -
#11500
0#
1!
#11600
1"
b0000000000000000000000000000000000000000000000000000000001000010 (
0!
#11700
1!
#11800
1#
0"
b00000000000000000000000000011101 +
b0110 $
18
00
0<
0Q
01
19
0=
0`
b1110 %
16
1:
0!
0?
0C
0L
1E
0H
1J
1X
0V
0M
0F
0X
1V
0K
0]
1[
1\
b01001100 &
b100101111010 .
b010010000000 -
#11900
0#
1!
#12000
1"
b0000000000000000000000000000000000000000000000000000000001010100 (
0!
#12100
1!
#12200
1#
0"
b00000000000000000000000000011110 +
b1100 $
04
1<
1Q
06
1>
1l
05
1=
1`
b1010 %
09
0=
0`
0!
0A
0G
1C
1L
0E
0R
1Y
1c
0\
0a
0Z
0i
1g
1e
0f
0m
b01111000 &
b111111110100 .
b000000000000 -
#12300
0#
1!
#12400
1"
b0000000000000000000000000000000000000000000000000000000001111000 (
0!
#12500
1!
#12600
1#
0"
b00000000000000000000000000011111 +
b1011 $
08
10
14
12
16
0:
b0001 %
1/
13
1;
02
06
0>
0l
0<
0Q
04
00
0!
1?
0O
0[
0W
0Y
0c
0\
0^
0g
0e
0j
b00001010 &
b000001010101 .
b00001011 &
#12700
0#
1!
#12800
1"
b0000000000000000000000000000000000000000000000000000000000001011 (
0!
#12900
1!
#13000
1#
0"
b00000000000000000000000000100000 +
b0101 $
03
17
0;
b1111 %
18
11
19
12
1:
10
0!
1A
1G
0C
0L
1H
1O
1[
0J
0V
1F
1V
0T
1W
1^
1g
1Y
1c
1U
1d
0c
1h
1f
1j
b01000011 &
b100110100011 .
b011001001000 -
#13100
0#
1!
#13200
1"
b0000000000000000000000000000000000000000000000000000000001001011 (
0!
#13300
1!
#13400
1#
0"
b00000000000000000000000000100001 +
b1011 $
08
14
1<
1Q
16
0:
1>
1l
15
09
1=
1`
13
07
1;
b1010 %
0/
03
0;
01
05
0=
0`
0!
1C
1L
1E
0H
0R
1J
1X
0V
0F
0X
1V
1W
0Y
0d
1c
1\
0^
0g
1Z
1g
1e
0h
0f
0m
b01110111 &
b111000111111 .
b000011000000 -
b01110110 &
#13500
0#
1!
#13600
1"
b0000000000000000000000000000000000000000000000000000000001101110 (
0!
#13700
1!
#13800
1#
0"
b00000000000000000000000000100010 +
b1110 $
18
00
02
1:
b0101 %
08
13
17
1;
15
19
1=
1`
06
0:
0>
0l
0<
0Q
04
0!
0J
0V
1M
0R
0W
1K
1]
0[
1^
1i
0g
0a
0\
0U
0c
0e
1f
b01000110 &
b100100101111 .
b010010010000 -
#13900
0#
1!
#14000
1"
b0000000000000000000000000000000000000000000000000000000001000110 (
0!
#14100
1!
#14200
1#
0"
b00000000000000000000000000100011 +
b0001 $
11
05
09
0=
0`
1/
03
07
0;
b1001 %
01
12
0!
0H
0C
0L
0M
0O
0]
1[
1T
0K
0[
0^
0i
1g
0Z
0g
0f
0j
b00001110 &
0?
0A
0G
b000001001000 .
b000000000000 -
0E
b00001001 &
b000001000000 .
#14300
0#
1!
#14400
1"
b0000000000000000000000000000000000000000000000000000000000001001 (
0!
#14500
1!
#14600
1#
0"
b00000000000000000000000000100100 +
b0010 $
02
16
0/
13
b1100 %
03
15
0!
1J
1V
1Y
1c
b00011001 &
b001011010000 .
b00011000 &
#14700
0#
1!
#14800
1"
b0000000000000000000000000000000000000000000000000000000000011000 (
0!
#14900
1!
#15000
1#
0"
b00000000000000000000000000100101 +
b1111 $
12
1:
1>
1l
11
19
1=
1`
b1111 %
18
1/
13
17
1;
1<
1Q
14
10
0!
1E
1D
1S
0Q
1O
1[
0R
0T
1W
1P
1b
0`
1^
1g
0a
0Y
0c
1\
1U
1c
1_
1n
0l
1Z
1i
0g
1f
1j
1k
b11010100 &
1B
1L
1@
1G
b101100111000 .
b110111100111 -
0E
1H
0J
0V
1M
1F
1V
1W
1K
1]
0[
1Y
1d
0c
0\
1e
b11100001 &
b110110100000 .
b111111111111 -
#15100
0#
1!
#15200
1"
b0000000000000000000000000000000000000000000000000000000011100001 (
0!
#15300
1!
#15400
1#
0"
b00000000000000000000000000100110 +
b1000 $
08
00
04
02
06
0:
01
05
09
0/
03
07
b0111 %
0>
0n
1l
0!
0@
0G
0B
0L
0H
0M
0O
0]
1[
0F
0V
0W
0K
0[
0Y
0d
1c
0^
0i
1g
0U
0c
0Z
0g
0e
0f
0m
0k
b01000001 &
b000100100100 -
b100000000000 .
b01000000 &
#15500
0#
1!
